PySDNSim/AutoScale.py
PySDNSim/Backend.py
PySDNSim/Config.py
PySDNSim/Experiment.py
PySDNSim/Host.py
PySDNSim/Job.py
PySDNSim/Log.py
PySDNSim/Microservice.py
PySDNSim/NetworkService.py
PySDNSim/__init__.py
PySDNSim-1.2.5.dist-info/LICENSE
PySDNSim-1.2.5.dist-info/METADATA
PySDNSim-1.2.5.dist-info/WHEEL
PySDNSim-1.2.5.dist-info/top_level.txt
PySDNSim-1.2.5.dist-info/RECORD
