Metadata-Version: 2.1
Name: PySDNSim
Version: 1.2.5
Summary: A simulation tool for microservices based SDN, with CloudSim Plus 7.3 as backend.
Author-email: Yifei Ren <ryf0510@live.com>
Project-URL: Homepage, https://github.com/ulfaric/PySDNSim
Project-URL: Bug Tracker, https://github.com/ulfaric/PySDNSim/issues
Classifier: Programming Language :: Python :: 3
Classifier: License :: OSI Approved :: GNU General Public License v3 (GPLv3)
Classifier: Operating System :: OS Independent
Requires-Python: >=3.7
License-File: LICENSE
